{
  "d": {
    "rows": [
      {
        "cells": [
          {
            "dateRangeValue": {
              "endDate": {
                "day": 26,
                "month": 7,
                "year": 2015
              },
              "startDate": {
                "day": 20,
                "month": 7,
                "year": 2015
              }
            },
            "textValue": "Jul 20, 2015 - Jul 26, 2015",
            "dataType": "urn:replicon:list-type:date-range"
          },
          {
            "calendarDayDurationValue": {
              "hours": 0,
              "minutes": 0,
              "seconds": 0
            },
            "textValue": "0.00",
            "dataType": "urn:replicon:list-type:calendar-day-duration"
          },
          {
            "calendarDayDurationValue": {
              "hours": 0,
              "minutes": 0,
              "seconds": 0
            },
            "textValue": "0.00",
            "dataType": "urn:replicon:list-type:calendar-day-duration"
          },
          {
            "calendarDayDurationValue": {
              "hours": 0,
              "minutes": 0,
              "seconds": 0
            },
            "textValue": "0.00",
            "dataType": "urn:replicon:list-type:calendar-day-duration"
          },
          {
            "calendarDayDurationValue": {
              "hours": 0,
              "minutes": 0,
              "seconds": 0
            },
            "textValue": "0.00",
            "dataType": "urn:replicon:list-type:calendar-day-duration"
          },
          {
            "textValue": "Jul 26, 2015",
            "dateValue": {
              "day": 26,
              "month": 7,
              "year": 2015
            },
            "dataType": "urn:replicon:list-type:date"
          },
          {
            "uri": "urn:replicon:approval-status:open",
            "dataType": "urn:replicon:list-type:object",
            "objectType": "urn:replicon:object-type:approval-status",
            "textValue": "Not Submitted"
          },
          {
            "slug": ".tilak/2015-7-20",
            "dataType": "urn:replicon:list-type:object",
            "objectType": "urn:replicon:object-type:timesheet",
            "uri": "urn:replicon-tenant:astro:timesheet:18e016e8-fb55-4126-a7c4-b4aa3ed6d2da"
          },
          {
            "calendarDayDurationValue": {
              "hours": 0,
              "minutes": 0,
              "seconds": 0
            },
            "textValue": "0.00",
            "dataType": "urn:replicon:list-type:calendar-day-duration"
          }
        ]
      },
      {
        "cells": [
          {
            "dateRangeValue": {
              "endDate": {
                "day": 19,
                "month": 7,
                "year": 2015
              },
              "startDate": {
                "day": 13,
                "month": 7,
                "year": 2015
              }
            },
            "textValue": "Jul 13, 2015 - Jul 19, 2015",
            "dataType": "urn:replicon:list-type:date-range"
          },
          {
            "calendarDayDurationValue": {
              "hours": 23,
              "minutes": 32,
              "seconds": 28
            },
            "textValue": "23.54",
            "dataType": "urn:replicon:list-type:calendar-day-duration"
          },
          {
            "calendarDayDurationValue": {
              "hours": 5,
              "minutes": 23,
              "seconds": 58
            },
            "textValue": "5.40",
            "dataType": "urn:replicon:list-type:calendar-day-duration"
          },
          {
            "calendarDayDurationValue": {
              "hours": 0,
              "minutes": 0,
              "seconds": 0
            },
            "textValue": "0.00",
            "dataType": "urn:replicon:list-type:calendar-day-duration"
          },
          {
            "calendarDayDurationValue": {
              "hours": 39,
              "minutes": 20,
              "seconds": 11
            },
            "textValue": "39.34",
            "dataType": "urn:replicon:list-type:calendar-day-duration"
          },
          {
            "textValue": "Jul 19, 2015",
            "dateValue": {
              "day": 19,
              "month": 7,
              "year": 2015
            },
            "dataType": "urn:replicon:list-type:date"
          },
          {
            "uri": "urn:replicon:approval-status:open",
            "dataType": "urn:replicon:list-type:object",
            "objectType": "urn:replicon:object-type:approval-status",
            "textValue": "Not Submitted"
          },
          {
            "slug": ".tilak/2015-7-13",
            "dataType": "urn:replicon:list-type:object",
            "objectType": "urn:replicon:object-type:timesheet",
            "uri": "urn:replicon-tenant:astro:timesheet:dbaff9ea-1ccc-4a19-a482-58acd7767dbd"
          },
          {
            "calendarDayDurationValue": {
              "hours": 28,
              "minutes": 56,
              "seconds": 26
            },
            "textValue": "28.94",
            "dataType": "urn:replicon:list-type:calendar-day-duration"
          }
        ]
      }
    ],
    "header": [
      {
        "uri": "urn:replicon:timesheet-list-column:timesheet-period",
        "displayName": "Timesheet Period"
      },
      {
        "uri": "urn:replicon:timesheet-list-column:regular-time-duration",
        "displayName": "Regular Hours"
      },
      {
        "uri": "urn:replicon:timesheet-list-column:overtime-duration",
        "displayName": "Overtime Hours"
      },
      {
        "uri": "urn:replicon:timesheet-list-column:time-off-duration",
        "displayName": "Time Off Hours"
      },
      {
        "uri": "urn:replicon:timesheet-list-column:total-duration",
        "displayName": "Total Hours"
      },
      {
        "uri": "urn:replicon:timesheet-list-column:due-date",
        "displayName": "Due Date"
      },
      {
        "uri": "urn:replicon:timesheet-list-column:approval-status",
        "displayName": "Approval Status"
      },
      {
        "uri": "urn:replicon:timesheet-list-column:timesheet",
        "displayName": "Timesheet"
      },
      {
        "uri": "urn:replicon:timesheet-list-column:total-payable-duration",
        "displayName": "Total Payable Hours"
      }
    ]
  }
}
