{
    "d":{
        "notInUsers":[
                      {
                      "totalWorkHours":{
                      "hours":0,
                      "minutes":0,
                      "seconds":0
                      },
                      "totalOvertimeHours":{
                      "hours":0,
                      "minutes":0,
                      "seconds":0
                      },
                      "user":{
                      "slug":"joanne",
                      "displayText":"Jacobs, Joanne",
                      "loginName":"Joanne",
                      "uri":"urn:replicon-tenant:astro:user:66"
                      },
                      "timeOffDetails":null,
                      "totalBreakHours":{
                      "hours":0,
                      "minutes":0,
                      "seconds":0
                      },
                      "timeSegments":[

                      ],
                      "totalRegularHours":{
                      "hours":0,
                      "minutes":0,
                      "seconds":0
                      }
                      },
                      {
                      "totalWorkHours":{
                      "hours":0,
                      "minutes":0,
                      "seconds":0
                      },
                      "totalOvertimeHours":{
                      "hours":0,
                      "minutes":0,
                      "seconds":0
                      },
                      "user":{
                      "slug":"suresh",
                      "displayText":"Kuppahally, Suresh",
                      "loginName":"Suresh",
                      "uri":"urn:replicon-tenant:astro:user:68"
                      },
                      "timeOffDetails":null,
                      "totalBreakHours":{
                      "hours":0,
                      "minutes":0,
                      "seconds":0
                      },
                      "timeSegments":[

                      ],
                      "totalRegularHours":{
                      "hours":0,
                      "minutes":0,
                      "seconds":0
                      }
                      },
                      {
                      "totalWorkHours":{
                      "hours":0,
                      "minutes":0,
                      "seconds":0
                      },
                      "totalOvertimeHours":{
                      "hours":0,
                      "minutes":0,
                      "seconds":0
                      },
                      "user":{
                      "slug":"raj",
                      "displayText":"Narayanaswamy, Raj",
                      "loginName":"Raj",
                      "uri":"urn:replicon-tenant:astro:user:65"
                      },
                      "timeOffDetails":null,
                      "totalBreakHours":{
                      "hours":0,
                      "minutes":0,
                      "seconds":0
                      },
                      "timeSegments":[

                      ],
                      "totalRegularHours":{
                      "hours":0,
                      "minutes":0,
                      "seconds":0
                      }
                      },
                      {
                      "totalWorkHours":{
                      "hours":0,
                      "minutes":0,
                      "seconds":0
                      },
                      "totalOvertimeHours":{
                      "hours":0,
                      "minutes":0,
                      "seconds":0
                      },
                      "user":{
                      "slug":"anil",
                      "displayText":"Panguluri, Anil",
                      "loginName":"Anil",
                      "uri":"urn:replicon-tenant:astro:user:67"
                      },
                      "timeOffDetails":null,
                      "totalBreakHours":{
                      "hours":0,
                      "minutes":0,
                      "seconds":0
                      },
                      "timeSegments":[

                      ],
                      "totalRegularHours":{
                      "hours":0,
                      "minutes":0,
                      "seconds":0
                      }
                      },
                      {
                      "totalWorkHours":{
                      "hours":0,
                      "minutes":0,
                      "seconds":0
                      },
                      "totalOvertimeHours":{
                      "hours":0,
                      "minutes":0,
                      "seconds":0
                      },
                      "user":{
                      "slug":"vinesha",
                      "displayText":"Perera, Vinesha",
                      "loginName":"Vinesha",
                      "uri":"urn:replicon-tenant:astro:user:64"
                      },
                      "timeOffDetails":null,
                      "totalBreakHours":{
                      "hours":0,
                      "minutes":0,
                      "seconds":0
                      },
                      "timeSegments":[

                      ],
                      "totalRegularHours":{
                      "hours":0,
                      "minutes":0,
                      "seconds":0
                      }
                      },
                      {
                      "totalWorkHours":{
                      "hours":0,
                      "minutes":0,
                      "seconds":0
                      },
                      "totalOvertimeHours":{
                      "hours":0,
                      "minutes":0,
                      "seconds":0
                      },
                      "user":{
                      "slug":"amit",
                      "displayText":"sharma, amit",
                      "loginName":"amit",
                      "uri":"urn:replicon-tenant:astro:user:74"
                      },
                      "timeOffDetails":null,
                      "totalBreakHours":{
                      "hours":0,
                      "minutes":0,
                      "seconds":0
                      },
                      "timeSegments":[

                      ],
                      "totalRegularHours":{
                      "hours":0,
                      "minutes":0,
                      "seconds":0
                      }
                      },
                      {
                      "totalWorkHours":{
                      "hours":0,
                      "minutes":0,
                      "seconds":21
                      },
                      "totalOvertimeHours":{
                      "hours":0,
                      "minutes":0,
                      "seconds":0
                      },
                      "user":{
                      "slug":"mike",
                      "displayText":"Testing, Mike",
                      "loginName":"Mike",
                      "uri":"urn:replicon-tenant:astro:user:69"
                      },
                      "timeOffDetails":null,
                      "totalBreakHours":{
                      "hours":0,
                      "minutes":0,
                      "seconds":0
                      },
                      "timeSegments":[
                                      {
                                      "timesheetTransferStatusUri":"urn:replicon:time-punch-timesheet-transfer-status:not-transferred",
                                      "endPunchActionUri":"urn:replicon:time-punch-action:out",
                                      "endPunchExtensionFields":{
                                      "values":[

                                      ],
                                      "bindings":[

                                      ]
                                      },
                                      "endPunchAgent":{
                                      "uri":null,
                                      "agentTypeUri":"urn:replicon:well-known-time-punch-agent-type:mobile",
                                      "displayText":"Mobile"
                                      },
                                      "endPunchAuditImages":[
                                                             {
                                                             "imageUri":"urn:replicon-tenant:astro:binary-object:f9b0d39c-900c-4678-9005-e2f26f1cb747",
                                                             "imageLink":{
                                                             "widthInPixels":1280,
                                                             "href":"https:\/\/demo1-gen3.replicon.com\/astro\/services\/BinaryObjectHandler.ashx?id=f9b0d39c900c46789005e2f26f1cb747",
                                                             "heightInPixels":850
                                                             }
                                                             },
                                                             {
                                                             "imageUri":"urn:replicon-tenant:astro:binary-object:03688b2e-e928-4781-80d4-11001d8d23eb",
                                                             "imageLink":{
                                                             "widthInPixels":32,
                                                             "href":"https:\/\/demo1-gen3.replicon.com\/astro\/services\/BinaryObjectHandler.ashx?id=03688b2ee928478180d411001d8d23eb",
                                                             "heightInPixels":32
                                                             }
                                                             }
                                                             ],
                                      "endPunchTime":{
                                      "minute":16,
                                      "hour":10,
                                      "second":37,
                                      "timeZone":{
                                      "uri":"urn:replicon:time-zone:america-los-angeles",
                                      "displayText":"(UTC-8:00) Pacific Standard Time"
                                      },
                                      "day":24,
                                      "month":4,
                                      "year":2015,
                                      "valueInUtc":{
                                      "minute":16,
                                      "hour":17,
                                      "second":37,
                                      "day":24,
                                      "month":4,
                                      "millisecond":0,
                                      "year":2015
                                      }
                                      },
                                      "owner":{
                                      "slug":"mike",
                                      "displayText":"Testing, Mike",
                                      "loginName":"Mike",
                                      "uri":"urn:replicon-tenant:astro:user:69"
                                      },
                                      "startPunchActionUri":null,
                                      "startPunchLastModificationTypeUri":null,
                                      "activity":null,
                                      "startPunchAgent":null,
                                      "startPunchValidationResult":null,
                                      "timesheetTransferErrorText":null,
                                      "startPunchTime":null,
                                      "endPunchGeolocation":{
                                      "address":"1800 Ellis Street, San Francisco, CA 94115, USA",
                                      "gps":{
                                      "accuracyInMeters":5,
                                      "latitudeInDegrees":37.7858,
                                      "longitudeInDegrees":-122.4064
                                      }
                                      },
                                      "startPunchUri":null,
                                      "breakType":null,
                                      "startPunchExtensionFields":null,
                                      "startPunchAuditImages":null,
                                      "endPunchUri":"urn:replicon-tenant:astro:time-punch:5461fb81-6188-46ac-bbce-acc4f1c64c7f",
                                      "endPunchValidationResult":{
                                      "validationTime":{
                                      "minute":16,
                                      "hour":17,
                                      "second":50,
                                      "day":24,
                                      "month":4,
                                      "millisecond":202,
                                      "year":2015
                                      },
                                      "validationMessages":[

                                      ]
                                      },
                                      "endPunchLastModificationTypeUri":"urn:replicon:time-punch-audit-record-modification-type:created-with-authentic-time",
                                      "startPunchGeolocation":null
                                      },
                                      {
                                      "timesheetTransferStatusUri":"urn:replicon:time-punch-timesheet-transfer-status:not-transferred",
                                      "endPunchActionUri":"urn:replicon:time-punch-action:out",
                                      "endPunchExtensionFields":{
                                      "values":[

                                      ],
                                      "bindings":[

                                      ]
                                      },
                                      "endPunchAgent":{
                                      "uri":null,
                                      "agentTypeUri":"urn:replicon:well-known-time-punch-agent-type:mobile",
                                      "displayText":"Mobile"
                                      },
                                      "endPunchAuditImages":[
                                                             {
                                                             "imageUri":"urn:replicon-tenant:astro:binary-object:61869485-22e5-4e07-ad1c-7232d7a524c7",
                                                             "imageLink":{
                                                             "widthInPixels":1500,
                                                             "href":"https:\/\/demo1-gen3.replicon.com\/astro\/services\/BinaryObjectHandler.ashx?id=6186948522e54e07ad1c7232d7a524c7",
                                                             "heightInPixels":1001
                                                             }
                                                             },
                                                             {
                                                             "imageUri":"urn:replicon-tenant:astro:binary-object:bfaa8cd7-950e-4d1f-a822-52e01d580326",
                                                             "imageLink":{
                                                             "widthInPixels":32,
                                                             "href":"https:\/\/demo1-gen3.replicon.com\/astro\/services\/BinaryObjectHandler.ashx?id=bfaa8cd7950e4d1fa82252e01d580326",
                                                             "heightInPixels":32
                                                             }
                                                             }
                                                             ],
                                      "endPunchTime":{
                                      "minute":16,
                                      "hour":10,
                                      "second":59,
                                      "timeZone":{
                                      "uri":"urn:replicon:time-zone:america-los-angeles",
                                      "displayText":"(UTC-8:00) Pacific Standard Time"
                                      },
                                      "day":24,
                                      "month":4,
                                      "year":2015,
                                      "valueInUtc":{
                                      "minute":16,
                                      "hour":17,
                                      "second":59,
                                      "day":24,
                                      "month":4,
                                      "millisecond":0,
                                      "year":2015
                                      }
                                      },
                                      "owner":{
                                      "slug":"mike",
                                      "displayText":"Testing, Mike",
                                      "loginName":"Mike",
                                      "uri":"urn:replicon-tenant:astro:user:69"
                                      },
                                      "startPunchActionUri":"urn:replicon:time-punch-action:in",
                                      "startPunchLastModificationTypeUri":"urn:replicon:time-punch-audit-record-modification-type:created-with-authentic-time",
                                      "activity":null,
                                      "startPunchAgent":{
                                      "uri":null,
                                      "agentTypeUri":"urn:replicon:well-known-time-punch-agent-type:mobile",
                                      "displayText":"Mobile"
                                      },
                                      "startPunchValidationResult":{
                                      "validationTime":{
                                      "minute":16,
                                      "hour":17,
                                      "second":54,
                                      "day":24,
                                      "month":4,
                                      "millisecond":71,
                                      "year":2015
                                      },
                                      "validationMessages":[

                                      ]
                                      },
                                      "timesheetTransferErrorText":null,
                                      "startPunchTime":{
                                      "minute":16,
                                      "hour":10,
                                      "second":45,
                                      "timeZone":{
                                      "uri":"urn:replicon:time-zone:america-los-angeles",
                                      "displayText":"(UTC-8:00) Pacific Standard Time"
                                      },
                                      "day":24,
                                      "month":4,
                                      "year":2015,
                                      "valueInUtc":{
                                      "minute":16,
                                      "hour":17,
                                      "second":45,
                                      "day":24,
                                      "month":4,
                                      "millisecond":0,
                                      "year":2015
                                      }
                                      },
                                      "endPunchGeolocation":{
                                      "address":"1800 Ellis Street, San Francisco, CA 94115, USA",
                                      "gps":{
                                      "accuracyInMeters":5,
                                      "latitudeInDegrees":37.7858,
                                      "longitudeInDegrees":-122.4064
                                      }
                                      },
                                      "startPunchUri":"urn:replicon-tenant:astro:time-punch:98218e8e-42ae-4fee-bcda-7c5d817c21ac",
                                      "breakType":null,
                                      "startPunchExtensionFields":{
                                      "values":[
                                      
                                      ],
                                      "bindings":[
                                      
                                      ]
                                      },
                                      "startPunchAuditImages":[
                                                               {
                                                               "imageUri":"urn:replicon-tenant:astro:binary-object:24a96229-70b7-4753-8dd9-aac101e6ad4d",
                                                               "imageLink":{
                                                               "widthInPixels":1008,
                                                               "href":"https:\/\/demo1-gen3.replicon.com\/astro\/services\/BinaryObjectHandler.ashx?id=24a9622970b747538dd9aac101e6ad4d",
                                                               "heightInPixels":669
                                                               }
                                                               },
                                                               {
                                                               "imageUri":"urn:replicon-tenant:astro:binary-object:2863e53b-fc77-4715-b2bb-b54b73dd7461",
                                                               "imageLink":{
                                                               "widthInPixels":32,
                                                               "href":"https:\/\/demo1-gen3.replicon.com\/astro\/services\/BinaryObjectHandler.ashx?id=2863e53bfc774715b2bbb54b73dd7461",
                                                               "heightInPixels":32
                                                               }
                                                               }
                                                               ],
                                      "endPunchUri":"urn:replicon-tenant:astro:time-punch:62441ede-5a91-4099-8734-74b810c4700a",
                                      "endPunchValidationResult":{
                                      "validationTime":{
                                      "minute":17,
                                      "hour":17,
                                      "second":9,
                                      "day":24,
                                      "month":4,
                                      "millisecond":998,
                                      "year":2015
                                      },
                                      "validationMessages":[
                                      
                                      ]
                                      },
                                      "endPunchLastModificationTypeUri":"urn:replicon:time-punch-audit-record-modification-type:created-with-authentic-time",
                                      "startPunchGeolocation":{
                                      "address":"1800 Ellis Street, San Francisco, CA 94115, USA",
                                      "gps":{
                                      "accuracyInMeters":5,
                                      "latitudeInDegrees":37.7858,
                                      "longitudeInDegrees":-122.4064
                                      }
                                      }
                                      },
                                      {
                                      "timesheetTransferStatusUri":"urn:replicon:time-punch-timesheet-transfer-status:not-transferred",
                                      "endPunchActionUri":"urn:replicon:time-punch-action:out",
                                      "endPunchExtensionFields":{
                                      "values":[
                                      
                                      ],
                                      "bindings":[
                                      
                                      ]
                                      },
                                      "endPunchAgent":{
                                      "uri":null,
                                      "agentTypeUri":"urn:replicon:well-known-time-punch-agent-type:mobile",
                                      "displayText":"Mobile"
                                      },
                                      "endPunchAuditImages":[
                                      
                                      ],
                                      "endPunchTime":{
                                      "minute":31,
                                      "hour":11,
                                      "second":17,
                                      "timeZone":{
                                      "uri":"urn:replicon:time-zone:america-los-angeles",
                                      "displayText":"(UTC-8:00) Pacific Standard Time"
                                      },
                                      "day":24,
                                      "month":4,
                                      "year":2015,
                                      "valueInUtc":{
                                      "minute":31,
                                      "hour":18,
                                      "second":17,
                                      "day":24,
                                      "month":4,
                                      "millisecond":0,
                                      "year":2015
                                      }
                                      },
                                      "owner":{
                                      "slug":"mike",
                                      "displayText":"Testing, Mike",
                                      "loginName":"Mike",
                                      "uri":"urn:replicon-tenant:astro:user:69"
                                      },
                                      "startPunchActionUri":"urn:replicon:time-punch-action:in",
                                      "startPunchLastModificationTypeUri":"urn:replicon:time-punch-audit-record-modification-type:created-with-authentic-time",
                                      "activity":null,
                                      "startPunchAgent":{
                                      "uri":null,
                                      "agentTypeUri":"urn:replicon:well-known-time-punch-agent-type:mobile",
                                      "displayText":"Mobile"
                                      },
                                      "startPunchValidationResult":{
                                      "validationTime":{
                                      "minute":31,
                                      "hour":18,
                                      "second":10,
                                      "day":24,
                                      "month":4,
                                      "millisecond":889,
                                      "year":2015
                                      },
                                      "validationMessages":[
                                      
                                      ]
                                      },
                                      "timesheetTransferErrorText":null,
                                      "startPunchTime":{
                                      "minute":31,
                                      "hour":11,
                                      "second":10,
                                      "timeZone":{
                                      "uri":"urn:replicon:time-zone:america-los-angeles",
                                      "displayText":"(UTC-8:00) Pacific Standard Time"
                                      },
                                      "day":24,
                                      "month":4,
                                      "year":2015,
                                      "valueInUtc":{
                                      "minute":31,
                                      "hour":18,
                                      "second":10,
                                      "day":24,
                                      "month":4,
                                      "millisecond":0,
                                      "year":2015
                                      }
                                      },
                                      "endPunchGeolocation":null,
                                      "startPunchUri":"urn:replicon-tenant:astro:time-punch:ed7951c6-1ee4-4152-aa0c-4b616aaa06f5",
                                      "breakType":null,
                                      "startPunchExtensionFields":{
                                      "values":[
                                      
                                      ],
                                      "bindings":[
                                      
                                      ]
                                      },
                                      "startPunchAuditImages":[
                                      
                                      ],
                                      "endPunchUri":"urn:replicon-tenant:astro:time-punch:b42e76a5-d645-46f4-920d-49af20dabf4b",
                                      "endPunchValidationResult":{
                                      "validationTime":{
                                      "minute":31,
                                      "hour":18,
                                      "second":18,
                                      "day":24,
                                      "month":4,
                                      "millisecond":81,
                                      "year":2015
                                      },
                                      "validationMessages":[
                                      
                                      ]
                                      },
                                      "endPunchLastModificationTypeUri":"urn:replicon:time-punch-audit-record-modification-type:created-with-authentic-time",
                                      "startPunchGeolocation":null
                                      }
                                      ],
                      "totalRegularHours":{
                      "hours":0,
                      "minutes":0,
                      "seconds":0
                      }
                      },
                      {
                      "totalWorkHours":{
                      "hours":0,
                      "minutes":0,
                      "seconds":0
                      },
                      "totalOvertimeHours":{
                      "hours":0,
                      "minutes":0,
                      "seconds":0
                      },
                      "user":{
                      "slug":"wiley",
                      "displayText":"Testing, Wiley",
                      "loginName":"Wiley",
                      "uri":"urn:replicon-tenant:astro:user:70"
                      },
                      "timeOffDetails":null,
                      "totalBreakHours":{
                      "hours":0,
                      "minutes":0,
                      "seconds":0
                      },
                      "timeSegments":[
                      
                      ],
                      "totalRegularHours":{
                      "hours":0,
                      "minutes":0,
                      "seconds":0
                      }
                      },
                      {
                      "totalWorkHours":{
                      "hours":0,
                      "minutes":0,
                      "seconds":0
                      },
                      "totalOvertimeHours":{
                      "hours":0,
                      "minutes":0,
                      "seconds":0
                      },
                      "user":{
                      "slug":"new",
                      "displayText":"User, New",
                      "loginName":"new",
                      "uri":"urn:replicon-tenant:astro:user:72"
                      },
                      "timeOffDetails":null,
                      "totalBreakHours":{
                      "hours":0,
                      "minutes":0,
                      "seconds":0
                      },
                      "timeSegments":[
                      
                      ],
                      "totalRegularHours":{
                      "hours":0,
                      "minutes":0,
                      "seconds":0
                      }
                      }
                      ],
        "onBreakUsers":[
        
        ],
        "clockedInUsers":[
        
        ]
    }
}